setup.py
rfw_utils/__init__.py
rfw_utils/functions.py
rfw_utils.egg-info/PKG-INFO
rfw_utils.egg-info/SOURCES.txt
rfw_utils.egg-info/dependency_links.txt
rfw_utils.egg-info/requires.txt
rfw_utils.egg-info/top_level.txt
rfw_utils.egg-info/zip-safe
rfw_utils/management/__init__.py
rfw_utils/management/commands/__init__.py
rfw_utils/management/commands/startapp_skeleton.py