Metadata-Version: 1.0
Name: rfw-utils
Version: 0.0.1
Summary: Speed up restframework develop
Home-page: https://github.com/h3l/rfw_utils
Author: helvetica
Author-email: xidianlz@gmail.com
License: MIT
Keywords: restframework utils
Platform: UNKNOWN
